README.txt
setup.py
ideogram/__init__.py
ideogram/converter.py
ideogram/ideogram.py
ideogram/importAnalysis.py
ideogram/options_list.py
ideogram/printer.py
ideogram/reader.py
ideogram/writer.py
ideogram.egg-info/PKG-INFO
ideogram.egg-info/SOURCES.txt
ideogram.egg-info/dependency_links.txt
ideogram.egg-info/requires.txt
ideogram.egg-info/top_level.txt
ideogram/polarfract/__init__.py
ideogram/polarfract/polarfract.py
ideogram/polarfract/test.py
ideogram/templates/colorbrewer.js
ideogram/templates/d3.js
ideogram/templates/d3.min.js
ideogram/templates/depth_layout.mustache
ideogram/templates/force_layout.mustache
ideogram/templates/moire_layout.mustache
ideogram/templates/pack_layout.mustache