Metadata-Version: 1.0
Name: ideogram
Version: 0.1
Summary: Python developers: Create a visual fingerprint for your project's source code!
Home-page: https://github.com/brmscheiner/ideogram
Author: Ben Scheiner
Author-email: brmscheiner@gmail.com
License: UNKNOWN
Platform: UNKNOWN
